dfddnsclient/__init__.py
dfddnsclient/app.py
dfddnsclient-1.4.dist-info/LICENSE
dfddnsclient-1.4.dist-info/METADATA
dfddnsclient-1.4.dist-info/WHEEL
dfddnsclient-1.4.dist-info/entry_points.txt
dfddnsclient-1.4.dist-info/top_level.txt
dfddnsclient-1.4.dist-info/RECORD
