Metadata-Version: 2.1
Name: dfddnsclient
Version: 1.4
Summary: this is a pilot ddns client
Home-page: https://github.com/dartfoxltd/dfddnsclient
Author: Dartfox.org
Author-email: mail@dartfox.org
License: UNKNOWN
Platform: UNKNOWN
License-File: LICENSE
Requires-Dist: flask
Requires-Dist: schedule
Requires-Dist: requests
